<annotation>
	<folder>train</folder>
	<filename>23.jpg</filename>
	<path>C:\Users\nigel\Desktop\object_detection_demo\data\images\train\23.jpg</path>
	<source>
		<database>Unknown</database>
	</source>
	<size>
		<width>800</width>
		<height>600</height>
		<depth>3</depth>
	</size>
	<segmented>0</segmented>
	<object>
		<name>fighter</name>
		<pose>Unspecified</pose>
		<truncated>0</truncated>
		<difficult>0</difficult>
		<bndbox>
			<xmin>160</xmin>
			<ymin>133</ymin>
			<xmax>585</xmax>
			<ymax>363</ymax>
		</bndbox>
	</object>
	<object>
		<name>fighter</name>
		<pose>Unspecified</pose>
		<truncated>0</truncated>
		<difficult>0</difficult>
		<bndbox>
			<xmin>92</xmin>
			<ymin>75</ymin>
			<xmax>420</xmax>
			<ymax>466</ymax>
		</bndbox>
	</object>
</annotation>
